odoo/addons/ssi_helpdesk_odoo_implementation/README.rst
odoo/addons/ssi_helpdesk_odoo_implementation/__init__.py
odoo/addons/ssi_helpdesk_odoo_implementation/__manifest__.py
odoo/addons/ssi_helpdesk_odoo_implementation/i18n/ssi_helpdesk_odoo_implementation.pot
odoo/addons/ssi_helpdesk_odoo_implementation/models/__init__.py
odoo/addons/ssi_helpdesk_odoo_implementation/models/helpdesk_ticket.py
odoo/addons/ssi_helpdesk_odoo_implementation/models/odoo_implementation.py
odoo/addons/ssi_helpdesk_odoo_implementation/static/description/icon.png
odoo/addons/ssi_helpdesk_odoo_implementation/views/helpdesk_ticket_views.xml
odoo14_addon_ssi_helpdesk_odoo_implementation-14.0.2.2.0.dist-info/METADATA
odoo14_addon_ssi_helpdesk_odoo_implementation-14.0.2.2.0.dist-info/WHEEL
odoo14_addon_ssi_helpdesk_odoo_implementation-14.0.2.2.0.dist-info/top_level.txt
odoo14_addon_ssi_helpdesk_odoo_implementation-14.0.2.2.0.dist-info/RECORD
