Metadata-Version: 2.1
Name: odoo14-addon-ssi_helpdesk_odoo_implementation
Version: 14.0.2.2.0
Summary: Helpdesk - Odoo Implementation Integration
Home-page: https://simetri-sinergi.id
Author: OpenSynergy Indonesia, PT. Simetri Sinergi Indonesia
License: AGPL-3
Classifier: Programming Language :: Python
Classifier: Framework :: Odoo
Classifier: Framework :: Odoo :: 14.0
Classifier: License :: OSI Approved :: GNU Affero General Public License v3
Requires-Python: >=3.6
Requires-Dist: odoo14-addon-ssi-helpdesk
Requires-Dist: odoo14-addon-ssi-odoo-implementation
Requires-Dist: odoo<14.1dev,>=14.0a
